flask_restsecurity/__init__.py
Flask_RestSecurity-0.0.1.dist-info/LICENSE
Flask_RestSecurity-0.0.1.dist-info/METADATA
Flask_RestSecurity-0.0.1.dist-info/WHEEL
Flask_RestSecurity-0.0.1.dist-info/top_level.txt
Flask_RestSecurity-0.0.1.dist-info/RECORD
