Metadata-Version: 2.1
Name: Flask-RestSecurity
Version: 0.0.1
Summary: Rest API Security OpenSource Project with Flask
Home-page: https://github.com/marcosstefani/flask-restsecurity
Author: Marcos Rosa
Author-email: marcos.cantor@gmail.com
License: UNKNOWN
Keywords: rest api authentication
Platform: UNKNOWN
Classifier: Development Status :: 3 - Alpha
Classifier: Intended Audience :: Developers
Classifier: Topic :: Software Development :: Build Tools
Classifier: Programming Language :: Python :: 3
Classifier: License :: OSI Approved :: BSD License
Classifier: Operating System :: OS Independent
Requires-Python: >=3.6
